BHPTNRremnant/__init__.py
BHPTNRremnant/analytical_fits.py
BHPTNRremnant/point_particle.py
BHPTNRremnant/remnant.py
BHPTNRremnant/.ipynb_checkpoints/analytical_fits-checkpoint.py
BHPTNRremnant/.ipynb_checkpoints/point_particle-checkpoint.py
BHPTNRremnant/.ipynb_checkpoints/remnant-checkpoint.py
BHPTNRremnant/data/BHPTNRSur1dq1e3_remnant.pickle
BHPTNRremnant/data/__init__.py
BHPTNRremnant/data/.ipynb_checkpoints/__init__-checkpoint.py
BHPTNRremnant/tests/__init__.py
BHPTNRremnant/tests/.ipynb_checkpoints/__init__-checkpoint.py
bhptnrremnant-0.0.3.dist-info/licenses/LICENSE
bhptnrremnant-0.0.3.dist-info/METADATA
bhptnrremnant-0.0.3.dist-info/WHEEL
bhptnrremnant-0.0.3.dist-info/top_level.txt
bhptnrremnant-0.0.3.dist-info/RECORD
