Metadata-Version: 2.4
Name: BHPTNRremnant
Version: 0.0.3
Summary: Python package for remnant black hole properties using perturbation theory and NR
Author: Scott Field, Gaurav Khanna
Author-email: Tousif Islam <tousifislam24@gmail.com>
License: MIT
Project-URL: Homepage, https://github.com/tousifislam/BHPTNR_Remnant
Project-URL: Repository, https://github.com/tousifislam/BHPTNR_Remnant
Project-URL: Documentation, https://github.com/tousifislam/BHPTNR_Remnant/blob/main/tutorials/tutorial.ipynb
Classifier: Intended Audience :: Science/Research
Classifier: License :: OSI Approved :: MIT License
Classifier: Natural Language :: English
Classifier: Programming Language :: Python :: 3
Classifier: Programming Language :: Python :: 3.7
Classifier: Programming Language :: Python :: 3.8
Classifier: Programming Language :: Python :: 3.9
Classifier: Programming Language :: Python :: 3.10
Classifier: Programming Language :: Python :: 3.11
Classifier: Programming Language :: Python :: 3.12
Classifier: Topic :: Scientific/Engineering
Classifier: Topic :: Scientific/Engineering :: Mathematics
Classifier: Topic :: Scientific/Engineering :: Physics
Requires-Python: >=3.7
License-File: LICENSE
Requires-Dist: numpy
Requires-Dist: matplotlib
Requires-Dist: scipy
Dynamic: license-file
